{
    "layout_data": {
        "units": {
            "user_size": 0.0005,
            "db_size": 5e-10
        },
        "cells": [
            {
                "cell_name": "INV",
                "properties": [
                    {
                        "type": "Rectangle",
                        "layer_number": 1,
                        "datatype_number": 0,
                        "coordinates": [
                            [
                                -1.08,
                                1.19
                            ],
                            [
                                -0.8200000000000001,
                                1.19
                            ],
                            [
                                -0.8200000000000001,
                                1.45
                            ],
                            [
                                -1.08,
                                1.45
                            ]
                        ]
                    },
                    {
                        "type": "Rectangle",
                        "layer_number": 1,
                        "datatype_number": 0,
                        "coordinates": [
                            [
                                -1.08,
                                2.13
                            ],
                            [
                                -0.8200000000000001,
                                2.13
                            ],
                            [
                                -0.8200000000000001,
                                2.39
                            ],
                            [
                                -1.08,
                                2.39
                            ]
                        ]
                    },
                    {
                        "type": "Rectangle",
                        "layer_number": 3,
                        "datatype_number": 0,
                        "coordinates": [
                            [
                                -0.21,
                                1.58
                            ],
                            [
                                -0.01,
                                1.58
                            ],
                            [
                                -0.01,
                                1.82
                            ],
                            [
                                -0.21,
                                1.82
                            ]
                        ]
                    },
                    {
                        "type": "Rectangle",
                        "layer_number": 3,
                        "datatype_number": 0,
                        "coordinates": [
                            [
                                -1.99,
                                1.58
                            ],
                            [
                                -1.79,
                                1.58
                            ],
                            [
                                -1.79,
                                1.82
                            ],
                            [
                                -1.99,
                                1.82
                            ]
                        ]
                    },
                    {
                        "type": "Rectangle",
                        "layer_number": 7,
                        "datatype_number": 0,
                        "coordinates": [
                            [
                                -0.45,
                                0.89
                            ],
                            [
                                -0.21,
                                0.89
                            ],
                            [
                                -0.21,
                                1.04
                            ],
                            [
                                -0.45,
                                1.04
                            ]
                        ]
                    },
                    {
                        "type": "Rectangle",
                        "layer_number": 7,
                        "datatype_number": 0,
                        "coordinates": [
                            [
                                -0.31,
                                1.58
                            ],
                            [
                                0.06,
                                1.58
                            ],
                            [
                                0.06,
                                1.82
                            ],
                            [
                                -0.31,
                                1.82
                            ]
                        ]
                    },
                    {
                        "type": "Rectangle",
                        "layer_number": 7,
                        "datatype_number": 0,
                        "coordinates": [
                            [
                                -0.45,
                                2.54
                            ],
                            [
                                -0.21,
                                2.54
                            ],
                            [
                                -0.21,
                                2.69
                            ],
                            [
                                -0.45,
                                2.69
                            ]
                        ]
                    },
                    {
                        "type": "Rectangle",
                        "layer_number": 7,
                        "datatype_number": 0,
                        "coordinates": [
                            [
                                -2.17,
                                0.89
                            ],
                            [
                                -0.21,
                                0.89
                            ],
                            [
                                -0.21,
                                1.0
                            ],
                            [
                                -2.17,
                                1.0
                            ]
                        ]
                    },
                    {
                        "type": "Rectangle",
                        "layer_number": 7,
                        "datatype_number": 0,
                        "coordinates": [
                            [
                                -2.17,
                                2.58
                            ],
                            [
                                -0.21,
                                2.58
                            ],
                            [
                                -0.21,
                                2.69
                            ],
                            [
                                -2.17,
                                2.69
                            ]
                        ]
                    },
                    {
                        "type": "Rectangle",
                        "layer_number": 7,
                        "datatype_number": 0,
                        "coordinates": [
                            [
                                -2.09,
                                1.58
                            ],
                            [
                                -1.72,
                                1.58
                            ],
                            [
                                -1.72,
                                1.82
                            ],
                            [
                                -2.09,
                                1.82
                            ]
                        ]
                    },
                    {
                        "type": "Rectangle",
                        "layer_number": 6,
                        "datatype_number": 0,
                        "coordinates": [
                            [
                                -0.17,
                                1.6400000000000001
                            ],
                            [
                                -0.05,
                                1.6400000000000001
                            ],
                            [
                                -0.05,
                                1.76
                            ],
                            [
                                -0.17,
                                1.76
                            ]
                        ]
                    },
                    {
                        "type": "Rectangle",
                        "layer_number": 6,
                        "datatype_number": 0,
                        "coordinates": [
                            [
                                -1.01,
                                1.26
                            ],
                            [
                                -0.89,
                                1.26
                            ],
                            [
                                -0.89,
                                1.3800000000000001
                            ],
                            [
                                -1.01,
                                1.3800000000000001
                            ]
                        ]
                    },
                    {
                        "type": "Rectangle",
                        "layer_number": 6,
                        "datatype_number": 0,
                        "coordinates": [
                            [
                                -1.01,
                                2.2
                            ],
                            [
                                -0.89,
                                2.2
                            ],
                            [
                                -0.89,
                                2.32
                            ],
                            [
                                -1.01,
                                2.32
                            ]
                        ]
                    },
                    {
                        "type": "Rectangle",
                        "layer_number": 6,
                        "datatype_number": 0,
                        "coordinates": [
                            [
                                -1.95,
                                1.6400000000000001
                            ],
                            [
                                -1.83,
                                1.6400000000000001
                            ],
                            [
                                -1.83,
                                1.76
                            ],
                            [
                                -1.95,
                                1.76
                            ]
                        ]
                    },
                    {
                        "type": "Rectangle",
                        "layer_number": 4,
                        "datatype_number": 0,
                        "coordinates": [
                            [
                                -1.1500000000000001,
                                2.05
                            ],
                            [
                                -0.75,
                                2.05
                            ],
                            [
                                -0.75,
                                2.45
                            ],
                            [
                                -1.1500000000000001,
                                2.45
                            ]
                        ]
                    },
                    {
                        "type": "Rectangle",
                        "layer_number": 5,
                        "datatype_number": 0,
                        "coordinates": [
                            [
                                -1.1500000000000001,
                                1.11
                            ],
                            [
                                -0.75,
                                1.11
                            ],
                            [
                                -0.75,
                                1.51
                            ],
                            [
                                -1.1500000000000001,
                                1.51
                            ]
                        ]
                    },
                    {
                        "type": "Rectangle",
                        "layer_number": 2,
                        "datatype_number": 0,
                        "coordinates": [
                            [
                                -0.7000000000000001,
                                1.83
                            ],
                            [
                                0.58,
                                1.83
                            ],
                            [
                                0.58,
                                2.54
                            ],
                            [
                                -0.7000000000000001,
                                2.54
                            ]
                        ]
                    },
                    {
                        "type": "Rectangle",
                        "layer_number": 2,
                        "datatype_number": 0,
                        "coordinates": [
                            [
                                -2.48,
                                1.83
                            ],
                            [
                                -0.7000000000000001,
                                1.83
                            ],
                            [
                                -0.7000000000000001,
                                2.54
                            ],
                            [
                                -2.48,
                                2.54
                            ]
                        ]
                    },
                    {
                        "type": "Rectangle",
                        "layer_number": 9,
                        "datatype_number": 0,
                        "coordinates": [
                            [
                                -0.45,
                                2.58
                            ],
                            [
                                0.58,
                                2.58
                            ],
                            [
                                0.58,
                                2.69
                            ],
                            [
                                -0.45,
                                2.69
                            ]
                        ]
                    },
                    {
                        "type": "Rectangle",
                        "layer_number": 9,
                        "datatype_number": 0,
                        "coordinates": [
                            [
                                -0.45,
                                0.89
                            ],
                            [
                                0.48,
                                0.89
                            ],
                            [
                                0.48,
                                1.0
                            ],
                            [
                                -0.45,
                                1.0
                            ]
                        ]
                    },
                    {
                        "type": "Rectangle",
                        "layer_number": 8,
                        "datatype_number": 0,
                        "coordinates": [
                            [
                                -0.39,
                                0.89
                            ],
                            [
                                -0.27,
                                0.89
                            ],
                            [
                                -0.27,
                                1.0
                            ],
                            [
                                -0.39,
                                1.0
                            ]
                        ]
                    },
                    {
                        "type": "Rectangle",
                        "layer_number": 8,
                        "datatype_number": 0,
                        "coordinates": [
                            [
                                -0.39,
                                2.58
                            ],
                            [
                                -0.27,
                                2.58
                            ],
                            [
                                -0.27,
                                2.69
                            ],
                            [
                                -0.39,
                                2.69
                            ]
                        ]
                    },
                    {
                        "type": "Rectangle",
                        "layer_number": 7,
                        "datatype_number": 1,
                        "coordinates": [
                            [
                                -1.6600000000000001,
                                2.58
                            ],
                            [
                                -1.5,
                                2.58
                            ],
                            [
                                -1.5,
                                2.69
                            ],
                            [
                                -1.6600000000000001,
                                2.69
                            ]
                        ]
                    },
                    {
                        "type": "Rectangle",
                        "layer_number": 7,
                        "datatype_number": 1,
                        "coordinates": [
                            [
                                -1.6600000000000001,
                                0.89
                            ],
                            [
                                -1.49,
                                0.89
                            ],
                            [
                                -1.49,
                                1.0
                            ],
                            [
                                -1.6600000000000001,
                                1.0
                            ]
                        ]
                    },
                    {
                        "type": "Rectangle",
                        "layer_number": 3,
                        "datatype_number": 0,
                        "coordinates": [
                            [
                                -0.009999999999999995,
                                2.0300000000000002
                            ],
                            [
                                -0.11,
                                2.0300000000000002
                            ],
                            [
                                -0.11,
                                1.4000000000000001
                            ],
                            [
                                -0.009999999999999995,
                                1.4000000000000001
                            ]
                        ]
                    },
                    {
                        "type": "Rectangle",
                        "layer_number": 3,
                        "datatype_number": 0,
                        "coordinates": [
                            [
                                -1.79,
                                2.0300000000000002
                            ],
                            [
                                -1.8900000000000001,
                                2.0300000000000002
                            ],
                            [
                                -1.8900000000000001,
                                1.4000000000000001
                            ],
                            [
                                -1.79,
                                1.4000000000000001
                            ]
                        ]
                    },
                    {
                        "type": "Rectangle",
                        "layer_number": 7,
                        "datatype_number": 0,
                        "coordinates": [
                            [
                                0.27,
                                2.22
                            ],
                            [
                                0.15,
                                2.22
                            ],
                            [
                                0.15,
                                1.33
                            ],
                            [
                                0.27,
                                1.33
                            ]
                        ]
                    },
                    {
                        "type": "Rectangle",
                        "layer_number": 7,
                        "datatype_number": 0,
                        "coordinates": [
                            [
                                -0.27,
                                1.31
                            ],
                            [
                                -0.39,
                                1.31
                            ],
                            [
                                -0.39,
                                0.89
                            ],
                            [
                                -0.27,
                                0.89
                            ]
                        ]
                    },
                    {
                        "type": "Rectangle",
                        "layer_number": 7,
                        "datatype_number": 0,
                        "coordinates": [
                            [
                                -0.39,
                                2.25
                            ],
                            [
                                -0.27,
                                2.25
                            ],
                            [
                                -0.27,
                                2.69
                            ],
                            [
                                -0.39,
                                2.69
                            ]
                        ]
                    },
                    {
                        "type": "Rectangle",
                        "layer_number": 7,
                        "datatype_number": 0,
                        "coordinates": [
                            [
                                -2.05,
                                1.31
                            ],
                            [
                                -2.17,
                                1.31
                            ],
                            [
                                -2.17,
                                0.89
                            ],
                            [
                                -2.05,
                                0.89
                            ]
                        ]
                    },
                    {
                        "type": "Rectangle",
                        "layer_number": 7,
                        "datatype_number": 0,
                        "coordinates": [
                            [
                                -2.17,
                                2.25
                            ],
                            [
                                -2.05,
                                2.25
                            ],
                            [
                                -2.05,
                                2.69
                            ],
                            [
                                -2.17,
                                2.69
                            ]
                        ]
                    },
                    {
                        "type": "Rectangle",
                        "layer_number": 7,
                        "datatype_number": 0,
                        "coordinates": [
                            [
                                -1.51,
                                2.22
                            ],
                            [
                                -1.6300000000000001,
                                2.22
                            ],
                            [
                                -1.6300000000000001,
                                1.33
                            ],
                            [
                                -1.51,
                                1.33
                            ]
                        ]
                    },
                    {
                        "type": "Rectangle",
                        "layer_number": 7,
                        "datatype_number": 0,
                        "coordinates": [
                            [
                                -0.8900000000000001,
                                1.45
                            ],
                            [
                                -1.01,
                                1.45
                            ],
                            [
                                -1.01,
                                0.89
                            ],
                            [
                                -0.8900000000000001,
                                0.89
                            ]
                        ]
                    },
                    {
                        "type": "Rectangle",
                        "layer_number": 7,
                        "datatype_number": 0,
                        "coordinates": [
                            [
                                -1.01,
                                2.13
                            ],
                            [
                                -0.8900000000000001,
                                2.13
                            ],
                            [
                                -0.8900000000000001,
                                2.69
                            ],
                            [
                                -1.01,
                                2.69
                            ]
                        ]
                    },
                    {
                        "type": "Rectangle",
                        "layer_number": 9,
                        "datatype_number": 0,
                        "coordinates": [
                            [
                                0.81,
                                2.69
                            ],
                            [
                                0.6699999999999999,
                                2.69
                            ],
                            [
                                0.6699999999999999,
                                0.89
                            ],
                            [
                                0.81,
                                0.89
                            ]
                        ]
                    },
                    {
                        "type": "Label",
                        "layer_number": 63,
                        "datatype_number": 0,
                        "coordinates": [
                            [
                                -1.6300000000000001,
                                2.88
                            ]
                        ],
                        "name": "vddp",
                        "rotation": 0.0
                    },
                    {
                        "type": "Label",
                        "layer_number": 63,
                        "datatype_number": 0,
                        "coordinates": [
                            [
                                -1.58,
                                0.79
                            ]
                        ],
                        "name": "vss",
                        "rotation": 0.0
                    },
                    {
                        "type": "Instance",
                        "origin": [
                            [
                                -0.11,
                                1.24
                            ]
                        ],
                        "bounding_box": [
                            [
                                -0.59,
                                1.04
                            ],
                            [
                                0.47,
                                1.56
                            ]
                        ],
                        "name": "nmos1v_0",
                        "rotation": 0.0,
                        "mirror_x": false
                    },
                    {
                        "type": "Instance",
                        "origin": [
                            [
                                -1.8900000000000001,
                                1.24
                            ]
                        ],
                        "bounding_box": [
                            [
                                -2.37,
                                1.04
                            ],
                            [
                                -1.31,
                                1.56
                            ]
                        ],
                        "name": "nmos1v_0",
                        "rotation": 0.0,
                        "mirror_x": false
                    },
                    {
                        "type": "Instance",
                        "origin": [
                            [
                                -0.11,
                                2.15
                            ]
                        ],
                        "bounding_box": [
                            [
                                -0.59,
                                1.95
                            ],
                            [
                                0.47,
                                2.4699999999999998
                            ]
                        ],
                        "name": "pmos1v_1",
                        "rotation": 0.0,
                        "mirror_x": false
                    },
                    {
                        "type": "Instance",
                        "origin": [
                            [
                                -1.8900000000000001,
                                2.15
                            ]
                        ],
                        "bounding_box": [
                            [
                                -2.37,
                                1.95
                            ],
                            [
                                -1.31,
                                2.4699999999999998
                            ]
                        ],
                        "name": "pmos1v_1",
                        "rotation": 0.0,
                        "mirror_x": false
                    }
                ]
            },
            {
                "cell_name": "nmos1v_0",
                "properties": [
                    {
                        "type": "Rectangle",
                        "layer_number": 1,
                        "datatype_number": 0,
                        "coordinates": [
                            [
                                0.2,
                                -0.06
                            ],
                            [
                                0.44,
                                -0.06
                            ],
                            [
                                0.44,
                                0.18
                            ],
                            [
                                0.2,
                                0.18
                            ]
                        ]
                    },
                    {
                        "type": "Rectangle",
                        "layer_number": 1,
                        "datatype_number": 0,
                        "coordinates": [
                            [
                                0.1,
                                0.0
                            ],
                            [
                                0.2,
                                0.0
                            ],
                            [
                                0.2,
                                0.12
                            ],
                            [
                                0.1,
                                0.12
                            ]
                        ]
                    },
                    {
                        "type": "Rectangle",
                        "layer_number": 1,
                        "datatype_number": 0,
                        "coordinates": [
                            [
                                -0.34,
                                -0.06
                            ],
                            [
                                -0.1,
                                -0.06
                            ],
                            [
                                -0.1,
                                0.18
                            ],
                            [
                                -0.34,
                                0.18
                            ]
                        ]
                    },
                    {
                        "type": "Rectangle",
                        "layer_number": 1,
                        "datatype_number": 0,
                        "coordinates": [
                            [
                                -0.1,
                                0.0
                            ],
                            [
                                0.0,
                                0.0
                            ],
                            [
                                0.0,
                                0.12
                            ],
                            [
                                -0.1,
                                0.12
                            ]
                        ]
                    },
                    {
                        "type": "Rectangle",
                        "layer_number": 1,
                        "datatype_number": 0,
                        "coordinates": [
                            [
                                0.0,
                                0.0
                            ],
                            [
                                0.1,
                                0.0
                            ],
                            [
                                0.1,
                                0.12
                            ],
                            [
                                0.0,
                                0.12
                            ]
                        ]
                    },
                    {
                        "type": "Rectangle",
                        "layer_number": 3,
                        "datatype_number": 0,
                        "coordinates": [
                            [
                                0.0,
                                -0.18
                            ],
                            [
                                0.1,
                                -0.18
                            ],
                            [
                                0.1,
                                -0.16
                            ],
                            [
                                0.0,
                                -0.16
                            ]
                        ]
                    },
                    {
                        "type": "Rectangle",
                        "layer_number": 3,
                        "datatype_number": 0,
                        "coordinates": [
                            [
                                0.0,
                                0.28
                            ],
                            [
                                0.1,
                                0.28
                            ],
                            [
                                0.1,
                                0.3
                            ],
                            [
                                0.0,
                                0.3
                            ]
                        ]
                    },
                    {
                        "type": "Rectangle",
                        "layer_number": 3,
                        "datatype_number": 0,
                        "coordinates": [
                            [
                                0.0,
                                -0.16
                            ],
                            [
                                0.1,
                                -0.16
                            ],
                            [
                                0.1,
                                0.0
                            ],
                            [
                                0.0,
                                0.0
                            ]
                        ]
                    },
                    {
                        "type": "Rectangle",
                        "layer_number": 3,
                        "datatype_number": 0,
                        "coordinates": [
                            [
                                0.0,
                                0.12
                            ],
                            [
                                0.1,
                                0.12
                            ],
                            [
                                0.1,
                                0.28
                            ],
                            [
                                0.0,
                                0.28
                            ]
                        ]
                    },
                    {
                        "type": "Rectangle",
                        "layer_number": 3,
                        "datatype_number": 0,
                        "coordinates": [
                            [
                                0.0,
                                0.0
                            ],
                            [
                                0.1,
                                0.0
                            ],
                            [
                                0.1,
                                0.12
                            ],
                            [
                                0.0,
                                0.12
                            ]
                        ]
                    },
                    {
                        "type": "Rectangle",
                        "layer_number": 7,
                        "datatype_number": 0,
                        "coordinates": [
                            [
                                0.26,
                                -0.06
                            ],
                            [
                                0.38,
                                -0.06
                            ],
                            [
                                0.38,
                                0.18
                            ],
                            [
                                0.26,
                                0.18
                            ]
                        ]
                    },
                    {
                        "type": "Rectangle",
                        "layer_number": 7,
                        "datatype_number": 0,
                        "coordinates": [
                            [
                                -0.28,
                                -0.06
                            ],
                            [
                                -0.16,
                                -0.06
                            ],
                            [
                                -0.16,
                                0.18
                            ],
                            [
                                -0.28,
                                0.18
                            ]
                        ]
                    },
                    {
                        "type": "Rectangle",
                        "layer_number": 6,
                        "datatype_number": 0,
                        "coordinates": [
                            [
                                0.26,
                                0.0
                            ],
                            [
                                0.38,
                                0.0
                            ],
                            [
                                0.38,
                                0.12
                            ],
                            [
                                0.26,
                                0.12
                            ]
                        ]
                    },
                    {
                        "type": "Rectangle",
                        "layer_number": 6,
                        "datatype_number": 0,
                        "coordinates": [
                            [
                                -0.28,
                                0.0
                            ],
                            [
                                -0.16,
                                0.0
                            ],
                            [
                                -0.16,
                                0.12
                            ],
                            [
                                -0.28,
                                0.12
                            ]
                        ]
                    },
                    {
                        "type": "Rectangle",
                        "layer_number": 4,
                        "datatype_number": 0,
                        "coordinates": [
                            [
                                -0.18,
                                -0.18
                            ],
                            [
                                0.28,
                                -0.18
                            ],
                            [
                                0.28,
                                0.3
                            ],
                            [
                                -0.18,
                                0.3
                            ]
                        ]
                    },
                    {
                        "type": "Rectangle",
                        "layer_number": 4,
                        "datatype_number": 0,
                        "coordinates": [
                            [
                                -0.48,
                                -0.2
                            ],
                            [
                                0.58,
                                -0.2
                            ],
                            [
                                0.58,
                                0.32
                            ],
                            [
                                -0.48,
                                0.32
                            ]
                        ]
                    },
                    {
                        "type": "Rectangle",
                        "layer_number": 85,
                        "datatype_number": 0,
                        "coordinates": [
                            [
                                -0.46,
                                -0.18
                            ],
                            [
                                0.56,
                                -0.18
                            ],
                            [
                                0.56,
                                0.3
                            ],
                            [
                                -0.46,
                                0.3
                            ]
                        ]
                    }
                ]
            },
            {
                "cell_name": "pmos1v_1",
                "properties": [
                    {
                        "type": "Rectangle",
                        "layer_number": 1,
                        "datatype_number": 0,
                        "coordinates": [
                            [
                                0.2,
                                -0.06
                            ],
                            [
                                0.44,
                                -0.06
                            ],
                            [
                                0.44,
                                0.18
                            ],
                            [
                                0.2,
                                0.18
                            ]
                        ]
                    },
                    {
                        "type": "Rectangle",
                        "layer_number": 1,
                        "datatype_number": 0,
                        "coordinates": [
                            [
                                0.1,
                                0.0
                            ],
                            [
                                0.2,
                                0.0
                            ],
                            [
                                0.2,
                                0.12
                            ],
                            [
                                0.1,
                                0.12
                            ]
                        ]
                    },
                    {
                        "type": "Rectangle",
                        "layer_number": 1,
                        "datatype_number": 0,
                        "coordinates": [
                            [
                                -0.34,
                                -0.06
                            ],
                            [
                                -0.1,
                                -0.06
                            ],
                            [
                                -0.1,
                                0.18
                            ],
                            [
                                -0.34,
                                0.18
                            ]
                        ]
                    },
                    {
                        "type": "Rectangle",
                        "layer_number": 1,
                        "datatype_number": 0,
                        "coordinates": [
                            [
                                -0.1,
                                0.0
                            ],
                            [
                                0.0,
                                0.0
                            ],
                            [
                                0.0,
                                0.12
                            ],
                            [
                                -0.1,
                                0.12
                            ]
                        ]
                    },
                    {
                        "type": "Rectangle",
                        "layer_number": 1,
                        "datatype_number": 0,
                        "coordinates": [
                            [
                                0.0,
                                0.0
                            ],
                            [
                                0.1,
                                0.0
                            ],
                            [
                                0.1,
                                0.12
                            ],
                            [
                                0.0,
                                0.12
                            ]
                        ]
                    },
                    {
                        "type": "Rectangle",
                        "layer_number": 3,
                        "datatype_number": 0,
                        "coordinates": [
                            [
                                0.0,
                                -0.18
                            ],
                            [
                                0.1,
                                -0.18
                            ],
                            [
                                0.1,
                                -0.16
                            ],
                            [
                                0.0,
                                -0.16
                            ]
                        ]
                    },
                    {
                        "type": "Rectangle",
                        "layer_number": 3,
                        "datatype_number": 0,
                        "coordinates": [
                            [
                                0.0,
                                0.28
                            ],
                            [
                                0.1,
                                0.28
                            ],
                            [
                                0.1,
                                0.3
                            ],
                            [
                                0.0,
                                0.3
                            ]
                        ]
                    },
                    {
                        "type": "Rectangle",
                        "layer_number": 3,
                        "datatype_number": 0,
                        "coordinates": [
                            [
                                0.0,
                                -0.16
                            ],
                            [
                                0.1,
                                -0.16
                            ],
                            [
                                0.1,
                                0.0
                            ],
                            [
                                0.0,
                                0.0
                            ]
                        ]
                    },
                    {
                        "type": "Rectangle",
                        "layer_number": 3,
                        "datatype_number": 0,
                        "coordinates": [
                            [
                                0.0,
                                0.12
                            ],
                            [
                                0.1,
                                0.12
                            ],
                            [
                                0.1,
                                0.28
                            ],
                            [
                                0.0,
                                0.28
                            ]
                        ]
                    },
                    {
                        "type": "Rectangle",
                        "layer_number": 3,
                        "datatype_number": 0,
                        "coordinates": [
                            [
                                0.0,
                                0.0
                            ],
                            [
                                0.1,
                                0.0
                            ],
                            [
                                0.1,
                                0.12
                            ],
                            [
                                0.0,
                                0.12
                            ]
                        ]
                    },
                    {
                        "type": "Rectangle",
                        "layer_number": 7,
                        "datatype_number": 0,
                        "coordinates": [
                            [
                                0.26,
                                -0.06
                            ],
                            [
                                0.38,
                                -0.06
                            ],
                            [
                                0.38,
                                0.18
                            ],
                            [
                                0.26,
                                0.18
                            ]
                        ]
                    },
                    {
                        "type": "Rectangle",
                        "layer_number": 7,
                        "datatype_number": 0,
                        "coordinates": [
                            [
                                -0.28,
                                -0.06
                            ],
                            [
                                -0.16,
                                -0.06
                            ],
                            [
                                -0.16,
                                0.18
                            ],
                            [
                                -0.28,
                                0.18
                            ]
                        ]
                    },
                    {
                        "type": "Rectangle",
                        "layer_number": 6,
                        "datatype_number": 0,
                        "coordinates": [
                            [
                                0.26,
                                0.0
                            ],
                            [
                                0.38,
                                0.0
                            ],
                            [
                                0.38,
                                0.12
                            ],
                            [
                                0.26,
                                0.12
                            ]
                        ]
                    },
                    {
                        "type": "Rectangle",
                        "layer_number": 6,
                        "datatype_number": 0,
                        "coordinates": [
                            [
                                -0.28,
                                0.0
                            ],
                            [
                                -0.16,
                                0.0
                            ],
                            [
                                -0.16,
                                0.12
                            ],
                            [
                                -0.28,
                                0.12
                            ]
                        ]
                    },
                    {
                        "type": "Rectangle",
                        "layer_number": 5,
                        "datatype_number": 0,
                        "coordinates": [
                            [
                                -0.18,
                                -0.18
                            ],
                            [
                                0.28,
                                -0.18
                            ],
                            [
                                0.28,
                                0.3
                            ],
                            [
                                -0.18,
                                0.3
                            ]
                        ]
                    },
                    {
                        "type": "Rectangle",
                        "layer_number": 5,
                        "datatype_number": 0,
                        "coordinates": [
                            [
                                -0.48,
                                -0.2
                            ],
                            [
                                0.58,
                                -0.2
                            ],
                            [
                                0.58,
                                0.32
                            ],
                            [
                                -0.48,
                                0.32
                            ]
                        ]
                    },
                    {
                        "type": "Rectangle",
                        "layer_number": 2,
                        "datatype_number": 0,
                        "coordinates": [
                            [
                                -0.46,
                                -0.18
                            ],
                            [
                                0.56,
                                -0.18
                            ],
                            [
                                0.56,
                                0.3
                            ],
                            [
                                -0.46,
                                0.3
                            ]
                        ]
                    }
                ]
            }
        ]
    }
}